rnalysis/__init__.py
rnalysis/enrichment.py
rnalysis/fastq.py
rnalysis/favicon.ico
rnalysis/filtering.py
rnalysis/general.py
rnalysis/data_files/latest_changelog.md
rnalysis/data_files/lookup_databases.json
rnalysis/data_files/tool_citations.json
rnalysis/data_files/uniprot_dataset_abbreviation_dict.json
rnalysis/data_files/r_templates/deseq2_comparison_parametric.R
rnalysis/data_files/r_templates/deseq2_covariate_parametric.R
rnalysis/data_files/r_templates/deseq2_install.R
rnalysis/data_files/r_templates/deseq2_lrt_parametric.R
rnalysis/data_files/r_templates/deseq2_run_parametric.R
rnalysis/data_files/r_templates/limma_comparison_parametric.R
rnalysis/data_files/r_templates/limma_covariate_parametric.R
rnalysis/data_files/r_templates/limma_install.R
rnalysis/data_files/r_templates/limma_lrt_parametric.R
rnalysis/data_files/r_templates/limma_run_parametric.R
rnalysis/data_files/r_templates/logging.R
rnalysis/data_files/r_templates/rsubread_featurecounts_run_parametric.R
rnalysis/data_files/r_templates/rsubread_install.R
rnalysis/data_files/r_templates/sessioninfo_run.R
rnalysis/data_files/report_misc/drawPath.js
rnalysis/data_files/report_misc/globalVars.js
rnalysis/data_files/report_misc/listeners.js
rnalysis/data_files/report_misc/options.json
rnalysis/data_files/report_misc/report_howto_link.html
rnalysis/data_files/report_templates/bootstrap.bundle.min.js
rnalysis/data_files/report_templates/bootstrap.min.css
rnalysis/data_files/report_templates/question-circle.svg
rnalysis/data_files/report_templates/vis-network.min.css
rnalysis/data_files/report_templates/vis-network.min.js
rnalysis/gui/__init__.py
rnalysis/gui/gui.py
rnalysis/gui/gui_graphics.py
rnalysis/gui/gui_quickstart.py
rnalysis/gui/gui_report.py
rnalysis/gui/gui_style.py
rnalysis/gui/gui_widgets.py
rnalysis/gui/gui_windows.py
rnalysis/gui/logo_small.png
rnalysis/gui/main.py
rnalysis/gui/splash.png
rnalysis/gui/splash_transparent.png
rnalysis/gui/icons/black_icon.png
rnalysis/gui/icons/blue_icon.png
RNAlysis-4.1.2.dist-info/LICENSE
RNAlysis-4.1.2.dist-info/METADATA
RNAlysis-4.1.2.dist-info/WHEEL
RNAlysis-4.1.2.dist-info/entry_points.txt
RNAlysis-4.1.2.dist-info/top_level.txt
RNAlysis-4.1.2.dist-info/RECORD
