Metadata-Version: 2.1
Name: RNAlysis
Version: 4.1.2
Summary: RNAlysis is an analysis software for RNA sequencing data. RNAlysis can help to filter, visualize, explore, analyze, and share your data. 
Home-page: https://github.com/GuyTeichman/RNAlysis
Author: Guy Teichman
Author-email: guyteichman@gmail.com
License: MIT license
Keywords: RNAlysis
Classifier: Development Status :: 5 - Production/Stable
Classifier: Intended Audience :: Science/Research
Classifier: License :: OSI Approved :: MIT License
Classifier: Natural Language :: English
Classifier: Programming Language :: Python :: 3 :: Only
Classifier: Programming Language :: Python :: 3.11
Classifier: Programming Language :: Python :: 3.12
Classifier: Programming Language :: Python :: 3.13
Classifier: Topic :: Scientific/Engineering :: Bio-Informatics
Classifier: Topic :: Scientific/Engineering :: Information Analysis
Classifier: Topic :: Scientific/Engineering :: Visualization
Requires-Python: >=3.10, <3.14
License-File: LICENSE
Requires-Dist: numpy<3,>=2.0.0
Requires-Dist: matplotlib>=3.10
Requires-Dist: seaborn>=0.13.2
Requires-Dist: statsmodels>=0.14.0
Requires-Dist: scikit-learn>=1.5.0
Requires-Dist: grid-strategy>=0.0.1
Requires-Dist: pyyaml>=6.0
Requires-Dist: UpSetPlot>=0.9.0
Requires-Dist: matplotlib-venn>=1.1.1
Requires-Dist: scipy>=1.14.0
Requires-Dist: pairwisedist>=1.3.1
Requires-Dist: requests>=2.32
Requires-Dist: graphviz>=0.20.3
Requires-Dist: joblib>=1.4.2
Requires-Dist: tqdm>=4.67
Requires-Dist: appdirs>=1.4.4
Requires-Dist: typing-extensions>=4.12
Requires-Dist: PyQt6>=6.9
Requires-Dist: qdarkstyle>=3
Requires-Dist: defusedxml>=0.7.1
Requires-Dist: aiohttp>=3.11
Requires-Dist: aiodns>=3.2
Requires-Dist: Brotli>=1.0.9
Requires-Dist: aiolimiter>=1.2
Requires-Dist: tenacity>=9.0.0
Requires-Dist: mslex>=1.3.0
Requires-Dist: nest-asyncio>=1.6.0
Requires-Dist: kmedoids>=0.5.3
Requires-Dist: polars[async,numpy,pandas,pyarrow]<1.31,>=1.30.0
Requires-Dist: pandas[parquet,performance]<3,>=2.2
Provides-Extra: all
Requires-Dist: pyvis>=0.3.2; extra == "all"
Requires-Dist: numba>=0.61.0; extra == "all"
Requires-Dist: networkx>=3.4.2; extra == "all"
Requires-Dist: xlmhglite>=1.1.1; extra == "all"
Requires-Dist: install-jdk>=1.1.0; extra == "all"
Requires-Dist: hdbscan>=0.8.40; extra == "all"
Requires-Dist: cutadapt>=5.0; extra == "all"
Provides-Extra: cutadapt
Requires-Dist: cutadapt>=5.0; extra == "cutadapt"
Provides-Extra: fastq
Requires-Dist: cutadapt>=5.0; extra == "fastq"
Provides-Extra: hdbscan
Requires-Dist: hdbscan>=0.8.40; extra == "hdbscan"
Provides-Extra: install-jdk
Requires-Dist: install-jdk>=1.1.0; extra == "install-jdk"
Provides-Extra: networkx
Requires-Dist: networkx>=3.4.2; extra == "networkx"
Provides-Extra: numba
Requires-Dist: numba>=0.61.0; extra == "numba"
Provides-Extra: picardtools
Requires-Dist: install-jdk>=1.1.0; extra == "picardtools"
Provides-Extra: pyvis
Requires-Dist: pyvis>=0.3.2; extra == "pyvis"
Provides-Extra: randomization
Requires-Dist: numba>=0.61.0; extra == "randomization"
Provides-Extra: reports
Requires-Dist: pyvis>=0.3.2; extra == "reports"
Requires-Dist: networkx>=3.4.2; extra == "reports"
Provides-Extra: single-set
Requires-Dist: xlmhglite>=1.1.1; extra == "single-set"
Provides-Extra: xlmhglite
Requires-Dist: xlmhglite>=1.1.1; extra == "xlmhglite"
